openg2p_beneficiary_portal_api/__init__.py
openg2p_beneficiary_portal_api/app.py
openg2p_beneficiary_portal_api/config.py
openg2p_beneficiary_portal_api/context.py
openg2p_beneficiary_portal_api/dependencies.py
openg2p_beneficiary_portal_api/exception.py
openg2p_beneficiary_portal_api/controllers/__init__.py
openg2p_beneficiary_portal_api/controllers/auth_controller.py
openg2p_beneficiary_portal_api/controllers/discovery_controller.py
openg2p_beneficiary_portal_api/controllers/document_file_controller.py
openg2p_beneficiary_portal_api/controllers/form_controller.py
openg2p_beneficiary_portal_api/controllers/oauth_controller.py
openg2p_beneficiary_portal_api/controllers/program_controller.py
openg2p_beneficiary_portal_api/errors/__init__.py
openg2p_beneficiary_portal_api/models/__init__.py
openg2p_beneficiary_portal_api/models/credentials.py
openg2p_beneficiary_portal_api/models/document_file.py
openg2p_beneficiary_portal_api/models/form.py
openg2p_beneficiary_portal_api/models/profile.py
openg2p_beneficiary_portal_api/models/program.py
openg2p_beneficiary_portal_api/models/orm/__init__.py
openg2p_beneficiary_portal_api/models/orm/auth_oauth_provider.py
openg2p_beneficiary_portal_api/models/orm/cycle_membership_orm.py
openg2p_beneficiary_portal_api/models/orm/cycle_orm.py
openg2p_beneficiary_portal_api/models/orm/document_file_orm.py
openg2p_beneficiary_portal_api/models/orm/document_store_orm.py
openg2p_beneficiary_portal_api/models/orm/document_tag_orm.py
openg2p_beneficiary_portal_api/models/orm/entitlement_orm.py
openg2p_beneficiary_portal_api/models/orm/formio_builder_orm.py
openg2p_beneficiary_portal_api/models/orm/partner_orm.py
openg2p_beneficiary_portal_api/models/orm/payment_orm.py
openg2p_beneficiary_portal_api/models/orm/program_membership_orm.py
openg2p_beneficiary_portal_api/models/orm/program_orm.py
openg2p_beneficiary_portal_api/models/orm/program_registrant_info_orm.py
openg2p_beneficiary_portal_api/models/orm/reg_id_orm.py
openg2p_beneficiary_portal_api-1.0.2.dist-info/METADATA
openg2p_beneficiary_portal_api-1.0.2.dist-info/WHEEL
openg2p_beneficiary_portal_api-1.0.2.dist-info/licenses/LICENSE
openg2p_beneficiary_portal_api-1.0.2.dist-info/RECORD
