Metadata-Version: 2.4
Name: openg2p-beneficiary-portal-api
Version: 1.0.2
Project-URL: Homepage, https://openg2p.org
Project-URL: Documentation, https://docs.openg2p.org/
Project-URL: Repository, https://github.com/OpenG2P/openg2p-beneficiary-portal-api
Project-URL: Source, https://github.com/OpenG2P/openg2p-beneficiary-portal-api
Author-email: OpenG2P <info@openg2p.org>
License-File: LICENSE
Classifier: License :: OSI Approved :: Mozilla Public License 2.0 (MPL 2.0)
Classifier: Operating System :: OS Independent
Classifier: Programming Language :: Python :: 3
Requires-Python: >=3.7
Requires-Dist: asyncpg
Requires-Dist: boto3
Requires-Dist: openg2p-fastapi-auth~=1.1.2
Requires-Dist: openg2p-fastapi-common~=1.1.2
Requires-Dist: psycopg2
Requires-Dist: python-slugify>=8.0.0
